[{"name":"argon2_dart","qualifiedName":"argon2_dart","href":"argon2_dart/argon2_dart-library.html","type":"library","overriddenDepth":0,"packageName":"dargon2","desc":"Library for Argon2 Hashing and verification in dart prrojects"},{"name":"argon2","qualifiedName":"argon2_dart.argon2","href":"argon2_dart/argon2.html","type":"top-level property","overriddenDepth":0,"packageName":"dargon2","desc":"The globally accessible instance of DArgon2 with Dart\nnative library loading","enclosedBy":{"name":"argon2_dart","type":"library","href":"argon2_dart/argon2_dart-library.html"}}]
